{
    "KPlugin": {
        "Description": "Runs ESLint on current file",
        "Description[ar]": "تشغيل ESLint على الملف الحالي",
        "Description[az]": "Cari faylda ESLint-i işə salır",
        "Description[bg]": "Изпълнява ESLint в текущия файл",
        "Description[ca@valencia]": "Executa ESLint sobre el fitxer actual",
        "Description[ca]": "Executa l'ESLint en el fitxer actual",
        "Description[cs]": "Spustí ESlint na aktuálním souboru",
        "Description[de]": "Führt ESLint für aktuelle Datei aus",
        "Description[en_GB]": "Runs ESLint on current file",
        "Description[eo]": "Rulas ESLint sur aktuala dosiero",
        "Description[es]": "Ejecuta ESLint en el archivo actual",
        "Description[eu]": "ESLint uneko fitxategian exekutatzen du",
        "Description[fi]": "Suorittaa ESLintin nykyiselle tiedostolle",
        "Description[fr]": "Exécute ESLint sur le fichier courant",
        "Description[gl]": "Executa ESLint no ficheiro actual.",
        "Description[he]": "הרצת ESLint על הקובץ הנוכחי",
        "Description[hu]": "ESLint futtatása a jelenlegi fájlon",
        "Description[ia]": "Executa ESLint dur file currente",
        "Description[it]": "Esegue ESLint sul file corrente",
        "Description[ka]": "მიმდინარე ფაილზე ESLint-ის გაშვება",
        "Description[ko]": "현재 파일에 ESLint 실행",
        "Description[lv]": "Pašreizējai datnei palaist „ESLint“",
        "Description[nl]": "Voert ESLint uit op huidig bestand",
        "Description[nn]": "Køyr ESLint på gjeldande fil",
        "Description[pl]": "Uruchamia ESLint na bieżącym pliku",
        "Description[pt]": "Executa o ESLint sobre o ficheiro actual",
        "Description[pt_BR]": "Executa ESLint no arquivo atual",
        "Description[ru]": "Запускает ESLint для текущего файла",
        "Description[sa]": "वर्तमानसञ्चिकायां ESLint चालयति",
        "Description[sk]": "Spustí ESLint na aktuálnom súbore",
        "Description[sl]": "Požene ESLint na trenutni datoteki",
        "Description[sv]": "Kör ESLint med aktuell fil",
        "Description[tr]": "Geçerli dosyada ESLint’i çalıştırır",
        "Description[uk]": "Запустити ESLint для поточного файла",
        "Description[vi]": "Chạy ESLint cho tệp hiện tại",
        "Description[x-test]": "xxRuns ESLint on current filexx",
        "Description[zh_CN]": "在当前文件运行 ESLint",
        "Description[zh_TW]": "為目前檔案執行 ESLint",
        "Name": "ESLint",
        "Name[ar]": "ESLint",
        "Name[az]": "ESLint",
        "Name[bg]": "ESLint",
        "Name[ca@valencia]": "ESLint",
        "Name[ca]": "ESLint",
        "Name[cs]": "ESLint",
        "Name[de]": "ESLint",
        "Name[en_GB]": "ESLint",
        "Name[eo]": "ESLint",
        "Name[es]": "ESLint",
        "Name[eu]": "ESLint",
        "Name[fi]": "ESLint",
        "Name[fr]": "ESLint",
        "Name[gl]": "ESLint",
        "Name[he]": "ESLint",
        "Name[hu]": "ESLint",
        "Name[ia]": "ESLint",
        "Name[it]": "ESLint",
        "Name[ka]": "ESLint",
        "Name[ko]": "ESLint",
        "Name[lv]": "ESLint",
        "Name[my]": "ESLint",
        "Name[nl]": "ESLint",
        "Name[nn]": "ESLint",
        "Name[pl]": "ESLint",
        "Name[pt]": "ESLint",
        "Name[pt_BR]": "ESLint",
        "Name[ru]": "ESLint",
        "Name[sa]": "ESLint",
        "Name[sk]": "ESLint",
        "Name[sl]": "ESLint",
        "Name[sv]": "ESLint",
        "Name[tr]": "ESLint",
        "Name[uk]": "ESLint",
        "Name[vi]": "ESLint",
        "Name[x-test]": "xxESLintxx",
        "Name[zh_CN]": "ESLint",
        "Name[zh_TW]": "ESLint"
    }
}
